{
  "type": "Feature",
  "stac_version": "1.1.0",
  "stac_extensions": [],
  "id": "AE_OPER_ALD_U_N_2B_20230423T050946_20230423T064020_0001",
  "geometry": {
    "type": "LineString",
    "coordinates": [
      [
        111.387194,
        85.234912
      ],
      [
        116.697935,
        85.17096
      ],
      [
        95.769747,
        85.309204
      ],
      [
        77.627311,
        84.923213
      ],
      [
        63.069216,
        84.143394
      ],
      [
        52.493715,
        83.077599
      ],
      [
        45.136603,
        81.817738
      ],
      [
        42.165537,
        81.158734
      ],
      [
        35.535799,
        79.066674
      ],
      [
        32.286955,
        77.621918
      ],
      [
        29.609793,
        76.157198
      ],
      [
        26.387718,
        73.926663
      ],
      [
        24.789831,
        72.407722
      ],
      [
        23.800996,
        71.827407
      ],
      [
        19.763313,
        66.301744
      ],
      [
        17.533674,
        61.633092
      ],
      [
        16.981718,
        60.875902
      ],
      [
        14.861553,
        55.417558
      ],
      [
        14.144108,
        53.216526
      ],
      [
        13.164321,
        49.122201
      ],
      [
        12.544888,
        47.574289
      ],
      [
        8.975043,
        31.806309
      ],
      [
        8.67136,
        30.223036
      ],
      [
        8.67823,
        29.407975
      ],
      [
        6.882096,
        20.721712
      ],
      [
        5.171352,
        11.207763
      ],
      [
        5.01411,
        9.600724
      ],
      [
        3.007953,
        -0.833796
      ],
      [
        2.723465,
        -3.084577
      ],
      [
        2.352465,
        -4.809434
      ],
      [
        2.312978,
        -4.648224
      ],
      [
        0.08616,
        -16.527528
      ],
      [
        359.924224,
        -17.316687
      ],
      [
        356.564401,
        -32.277339
      ],
      [
        353.45865,
        -42.398871
      ],
      [
        351.146367,
        -48.587376
      ],
      [
        350.725833,
        -50.16595
      ],
      [
        348.50132,
        -54.758473
      ],
      [
        345.877976,
        -59.322977
      ],
      [
        345.011825,
        -60.174131
      ],
      [
        344.768668,
        -60.659167
      ],
      [
        341.683806,
        -64.537027
      ],
      [
        339.535698,
        -66.753099
      ],
      [
        338.404873,
        -67.427434
      ],
      [
        336.498265,
        -69.01781
      ],
      [
        333.490283,
        -71.002454
      ],
      [
        329.676123,
        -72.900467
      ],
      [
        326.30973,
        -74.357771
      ],
      [
        320.625848,
        -76.256995
      ],
      [
        313.37903,
        -78.011779
      ],
      [
        303.756485,
        -79.483202
      ],
      [
        295.663881,
        -80.186228
      ],
      [
        281.903512,
        -80.980633
      ],
      [
        266.533889,
        -81.261008
      ],
      [
        251.685318,
        -80.709869
      ],
      [
        238.456931,
        -79.857106
      ],
      [
        228.066652,
        -78.486064
      ],
      [
        218.0694,
        -76.178709
      ],
      [
        212.124709,
        -74.335242
      ],
      [
        211.229687,
        -73.723418
      ],
      [
        206.335168,
        -71.645777
      ],
      [
        205.167368,
        -70.944386
      ],
      [
        202.055036,
        -68.816172
      ],
      [
        199.344848,
        -66.663866
      ],
      [
        198.856786,
        -65.882577
      ],
      [
        197.752807,
        -64.889246
      ],
      [
        195.963655,
        -62.796498
      ],
      [
        193.239901,
        -59.201104
      ],
      [
        191.733697,
        -56.948214
      ],
      [
        189.666913,
        -53.145083
      ],
      [
        187.019929,
        -46.99276
      ],
      [
        185.926593,
        -43.892465
      ],
      [
        183.701212,
        -36.897834
      ],
      [
        183.612142,
        -35.940209
      ],
      [
        182.230716,
        -31.426309
      ],
      [
        182.028939,
        -29.978497
      ],
      [
        179.859185,
        -21.216863
      ],
      [
        179.829277,
        -20.404563
      ],
      [
        179.871807,
        -20.550667
      ],
      [
        178.101741,
        -12.541067
      ],
      [
        176.146459,
        -2.266205
      ],
      [
        176.115423,
        -1.45476
      ],
      [
        175.847112,
        -0.686241
      ],
      [
        173.115134,
        15.167913
      ],
      [
        169.755925,
        32.701245
      ],
      [
        169.933107,
        32.268595
      ],
      [
        168.015166,
        40.426217
      ],
      [
        167.839559,
        42.02452
      ],
      [
        165.516914,
        50.653619
      ],
      [
        164.723749,
        52.993374
      ],
      [
        164.771267,
        53.504098
      ],
      [
        163.837285,
        56.289639
      ],
      [
        162.639251,
        59.558797
      ],
      [
        161.207243,
        62.508082
      ],
      [
        161.465539,
        62.228388
      ],
      [
        160.091338,
        64.686205
      ],
      [
        159.458468,
        65.439971
      ],
      [
        159.291632,
        66.393635
      ],
      [
        158.90116,
        67.018859
      ],
      [
        158.013202,
        67.752116
      ],
      [
        156.465523,
        70.06829
      ],
      [
        154.98692,
        71.578773
      ],
      [
        154.310693,
        72.656398
      ],
      [
        153.385751,
        73.089787
      ],
      [
        152.555111,
        73.846588
      ],
      [
        151.925791,
        74.783774
      ],
      [
        150.511455,
        75.337591
      ],
      [
        146.758025,
        77.548668
      ],
      [
        143.379915,
        78.977163
      ],
      [
        141.358904,
        80.016603
      ],
      [
        136.210869,
        81.365151
      ],
      [
        130.938109,
        82.416558
      ],
      [
        125.971731,
        83.12047
      ],
      [
        126.913518,
        83.022566
      ],
      [
        121.581901,
        83.520567
      ]
    ]
  },
  "bbox": [
    0.08616,
    -81.261008,
    359.924224,
    85.309204
  ],
  "properties": {
    "start_time": "2023-04-23T05:09:09.149184Z",
    "end_time": "2023-04-23T06:39:42.189962Z",
    "platform": "Aeolus",
    "instrument": "ALADIN",
    "product": "L2B",
    "wind_type": "Rayleigh",
    "track_point_count_original": 475,
    "track_point_count_simplified": 115,
    "simplification_tolerance_deg": 0.1,
    "fixed_altitude_km": 24.0,
    "datetime": "2023-04-23T05:09:09.149184Z"
  },
  "links": [
    {
      "rel": "root",
      "href": "../collection.json",
      "type": "application/json"
    },
    {
      "rel": "collection",
      "href": "../collection.json",
      "type": "application/json"
    },
    {
      "rel": "parent",
      "href": "../collection.json",
      "type": "application/json"
    }
  ],
  "assets": {
    "curtain_preview": {
      "href": "https://esa-vires.github.io/vertical_profile_prototype/assets/AE_OPER_ALD_U_N_2B_20230423T050946_20230423T064020_0001.png",
      "type": "image/png",
      "title": "Aeolus Rayleigh Curtain Plot",
      "roles": [
        "visual"
      ]
    }
  },
  "collection": "aeolus-l2b-rayleigh-track"
}